{
  "ts": 1777773047,
  "app_version": "0.6.0-demo-core-prebuild",
  "audit": {
    "ok": true,
    "no_network": true,
    "go_for_apk_build_later": true,
    "score_pct": 100.0,
    "min_score_pct": 90.0,
    "passed_required": 8,
    "total_required": 8,
    "failed_required": [],
    "order_endpoint_flags": [],
    "checks": [
      {
        "key": "logs/full_system_status_report.json",
        "title": "logs/full_system_status_report.json",
        "required": true,
        "ok": true,
        "detail": {
          "exists": true,
          "size": 79458
        }
      },
      {
        "key": "logs/health_report.json",
        "title": "logs/health_report.json",
        "required": true,
        "ok": true,
        "detail": {
          "exists": true,
          "size": 15662
        }
      },
      {
        "key": "logs/firstrun_readiness_report.json",
        "title": "logs/firstrun_readiness_report.json",
        "required": true,
        "ok": true,
        "detail": {
          "exists": true,
          "size": 40783
        }
      },
      {
        "key": "logs/release_candidate_report.json",
        "title": "logs/release_candidate_report.json",
        "required": true,
        "ok": true,
        "detail": {
          "exists": true,
          "size": 60615
        }
      },
      {
        "key": "logs/ui_route_report.json",
        "title": "logs/ui_route_report.json",
        "required": true,
        "ok": true,
        "detail": {
          "exists": true,
          "size": 8118
        }
      },
      {
        "key": "logs/apk_build_gate_report.json",
        "title": "logs/apk_build_gate_report.json",
        "required": true,
        "ok": true,
        "detail": {
          "exists": true,
          "size": 2958
        }
      },
      {
        "key": "logs/apk_artifact_manifest.json",
        "title": "logs/apk_artifact_manifest.json",
        "required": true,
        "ok": true,
        "detail": {
          "exists": true,
          "size": 2089
        }
      },
      {
        "key": "plain_secrets",
        "title": "Plain secret fájl ne legyen",
        "required": true,
        "ok": true,
        "detail": {
          "plain_found": []
        }
      }
    ],
    "will_build_now": false,
    "apk_build_touched": false,
    "order_endpoint_used": false,
    "message": "Final prebuild audit NO NETWORK MINI kész. APK build nincs."
  },
  "go_nogo": {
    "ok": true,
    "verdict": "GO",
    "score_pct": 100.0,
    "failed_count": 0,
    "failed_required": [],
    "next_steps": [
      "Kód oldalon APK build előtti állapot jó.",
      "Következő: kézi UI indítás/átkattintás vagy APK build pipeline előkészítés.",
      "Valódi live order továbbra sem aktív."
    ],
    "will_build_now": false,
    "apk_build_touched": false,
    "order_endpoint_used": false
  },
  "order_endpoint_used": false,
  "apk_build_touched": false
}